
{
  "professional_terms": {
    "人工智能": ["人工只能", "人工职能", "人工智囊", "任工智能"],
    "机器学习": ["机器雪习", "机器学西", "机器学细", "机气学习"],
    "深度学习": ["深度雪习", "深度学细", "申度学习", "身度学习"],
    "神经网络": ["神经网洛", "神经忘络", "申经网络", "神径网络"],
    "区块链": ["去块链", "区快链", "驱块链", "区块连"],
    "大数据": ["大书据", "大数具", "大属据", "大数居"],
    "云计算": ["运计算", "云机算", "运机算", "云计蒜"],
    "物联网": ["物连网", "无联网", "务联网", "物恋网"],
    "算法": ["算发", "蒜法", "算花", "算法"],
    "编程": ["编成", "便程", "编称", "变程"],
    
    "影视制作": ["影视制做", "影视治作", "应视制作"],
    "电视剧": ["电视局", "电视剧", "电视据"],
    "电影": ["电应", "店影", "电影"],
    "综艺": ["综艺", "宗艺", "综议"],
    "纪录片": ["记录片", "纪录篇", "纪绿片"],
    "动画片": ["动话片", "动画篇", "动划片"],
    "微电影": ["微店影", "微电应", "为电影"],
    "网剧": ["网局", "网据", "忘剧"],
    "网络剧": ["网络局", "网络据", "忘络剧"],
    "短剧": ["短局", "断剧", "短据"],
    "迷你剧": ["迷你局", "谜你剧", "米你剧"],
    
    "票房": ["票房", "票防", "飘房"],
    "口碑": ["口杯", "口背", "扣碑"],
    "评分": ["评份", "萍分", "评芬"],
    "收视率": ["收视律", "收视滤", "守视率"],
    "点击率": ["点机率", "点记率", "电击率"],
    "播放量": ["播放亮", "波放量", "播房量"],
    "观看量": ["观看亮", "关看量", "观看良"],
    "下载量": ["下载亮", "夏载量", "下在量"],
    "分享量": ["分想量", "份享量", "分享亮"],
    "转发量": ["转发亮", "转法量", "专发量"],
    "评论量": ["评论亮", "萍论量", "评伦量"],
    "点赞量": ["点赞亮", "电赞量", "点站量"],
    
    "院线": ["院线", "缘线", "院县"],
    "首映": ["首应", "手映", "守映"],
    "首播": ["首波", "手播", "守播"],
    "重播": ["重波", "中播", "种播"],
    "回放": ["回房", "回防", "归放"],
    "点播": ["点波", "电播", "店播"],
    "直播": ["直波", "植播", "志播"],
    "录播": ["录波", "路播", "绿播"],
    "转播": ["转波", "专播", "传播"],
    "联播": ["联波", "连播", "练播"],
    "同播": ["同波", "通播", "童播"],
    "首发": ["首法", "手发", "守发"],
    "独播": ["独波", "毒播", "读播"],
    "全网": ["全忘", "权网", "全网"],
    "全平台": ["全平台", "权平台", "全评台"],
    
    "演技": ["演技", "言技", "眼技"],
    "台词": ["台词", "抬词", "台磁"],
    "对白": ["对百", "对摆", "对败"],
    "独白": ["独百", "独摆", "读白"],
    "旁白": ["旁百", "傍白", "膀白"],
    "画外音": ["画外因", "话外音", "画歪音"],
    "配音": ["配因", "陪音", "培音"],
    "原声": ["原声", "元声", "圆声"],
    "现场": ["现场", "县场", "现厂"],
    "实景": ["实景", "是景", "石景"],
    "内景": ["内景", "那景", "纳景"],
    "外景": ["外景", "歪景", "外井"],
    "夜景": ["夜景", "也景", "野景"],
    "日景": ["日景", "日井", "热景"],
    
    "剧组": ["据组", "剧族", "局组"],
    "剧团": ["据团", "剧团", "局团"],
    "片场": ["片场", "篇场", "偏场"],
    "现场": ["现场", "县场", "现厂"],
    "工作室": ["工作是", "工做室", "工作室"],
    "制作公司": ["制作公思", "制做公司", "质作公司"],
    "影视公司": ["影视公思", "应视公司", "影视工司"],
    "传媒公司": ["传媒公思", "船媒公司", "传煤公司"],
    "娱乐公司": ["娱乐公思", "愉乐公司", "于乐公司"],
    "经纪公司": ["经济公司", "精纪公司", "经记公司"],
    
    "开机": ["开鸡", "开机", "凯机"],
    "杀青": ["杀青", "杀清", "沙青"],
    "关机": ["关鸡", "关机", "观机"],
    "收工": ["收工", "守工", "受工"],
    "收场": ["收场", "守场", "受场"],
    "收官": ["收关", "守官", "受官"],
    "封镜": ["封镜", "风镜", "峰镜"],
    "定档": ["定当", "订档", "定档"],
    "撤档": ["撤当", "撤档", "车档"],
    "改档": ["改当", "该档", "改档"],
    "延档": ["延当", "言档", "研档"],
    "提档": ["提当", "题档", "体档"],
    
    "宣发": ["宣法", "选发", "宣发"],
    "路演": ["路眼", "路言", "陆演"],
    "发布会": ["发部会", "发补会", "法布会"],
    "首映礼": ["首应礼", "手映礼", "守映礼"],
    "庆功宴": ["庆工宴", "请功宴", "庆功晏"],
    "答谢宴": ["答谢晏", "达谢宴", "答写宴"],
    "媒体见面会": ["媒体间面会", "煤体见面会", "媒体见面汇"],
    "粉丝见面会": ["粉丝间面会", "粉思见面会", "粉丝见面汇"],
    "观众见面会": ["观众间面会", "关众见面会", "观众见面汇"]
  },
  
  "polyphone_corrections": {
    "银行": {
      "错误": ["银航", "银杭", "音行", "印行", "阴行"],
      "关键词": ["金融", "存款", "贷款", "账户", "转账", "利息", "ATM", "信用卡", "储蓄"]
    },
    "音乐": {
      "错误": ["音月", "阴乐", "因乐", "音了", "音勒"],
      "关键词": ["歌曲", "演出", "乐器", "唱歌", "音符", "旋律", "歌手", "演唱", "作曲"]
    },
    "重要": {
      "错误": ["种要", "中要", "重药", "虫要", "重耀"],
      "关键词": ["重点", "主要", "关键", "核心", "重大", "紧要", "要紧"]
    },
    "背景": {
      "错误": ["被景", "倍景", "背井", "背经", "悲景"],
      "关键词": ["环境", "情况", "历史", "经历", "出身", "来历", "身世"]
    },
    "教育": {
      "错误": ["叫育", "交育", "教鱼", "较育", "角育"],
      "关键词": ["学校", "老师", "学生", "课程", "学习", "培养", "教学"]
    },
    "医院": {
      "错误": ["医源", "一院", "衣院", "医员", "医原"],
      "关键词": ["医生", "护士", "病人", "治疗", "手术", "看病", "住院"]
    },
    "结果": {
      "错误": ["结过", "接果", "洁果", "结国", "截果"],
      "关键词": ["结论", "答案", "成果", "后果", "效果", "产生", "导致"]
    },
    "处理": {
      "错误": ["触理", "处力", "初理", "楚理", "储理"],
      "关键词": ["解决", "应对", "办理", "处置", "操作", "执行"]
    },
    "角色": {
      "错误": ["脚色", "叫色", "角射", "觉色", "交色"],
      "关键词": ["人物", "演员", "主角", "配角", "扮演", "饰演"]
    },
    "数据": {
      "错误": ["数具", "属据", "书据", "数居", "树据"],
      "关键词": ["信息", "资料", "统计", "记录", "档案", "文件"]
    },
    "模型": {
      "错误": ["模行", "摸型", "魔型", "母型", "末型"],
      "关键词": ["样板", "范例", "原型", "设计", "建模", "框架"]
    },
    "网络": {
      "错误": ["网洛", "忘络", "网落", "网络", "往络"],
      "关键词": ["互联网", "网站", "在线", "联网", "上网", "网页"]
    },
    "系统": {
      "错误": ["细统", "系通", "西统", "戏统", "系童"],
      "关键词": ["软件", "程序", "应用", "平台", "操作", "管理"]
    },
    "技术": {
      "错误": ["技述", "记术", "技树", "即术", "急术"],
      "关键词": ["科技", "方法", "工艺", "技能", "专业", "创新"]
    },
    "发展": {
      "错误": ["发战", "法展", "发占", "发沾", "法战"],
      "关键词": ["进步", "成长", "扩大", "壮大", "提升", "改善"]
    },
    "社会": {
      "错误": ["社汇", "设会", "舍会", "射会", "社慧"],
      "关键词": ["人群", "群体", "公众", "民众", "集体", "团体"]
    },
    "经济": {
      "错误": ["经记", "精济", "经际", "经挤", "经计"],
      "关键词": ["金融", "财政", "商业", "贸易", "投资", "收入"]
    },
    "文化": {
      "错误": ["文话", "闻化", "文划", "文华", "温化"],
      "关键词": ["传统", "习俗", "艺术", "精神", "思想", "价值"]
    },
    "历史": {
      "错误": ["立史", "历时", "厉史", "例史", "力史"],
      "关键词": ["过去", "古代", "朝代", "年代", "事件", "记录"]
    },
    "现代": {
      "错误": ["县代", "现带", "显代", "现待", "现戴"],
      "关键词": ["当代", "如今", "现在", "今天", "当前", "目前"]
    },
    "传统": {
      "错误": ["传童", "船统", "传通", "传桶", "穿统"],
      "关键词": ["古老", "习俗", "文化", "祖先", "世代", "继承"]
    },
    "创新": {
      "错误": ["创心", "闯新", "创辛", "窗新", "床新"],
      "关键词": ["革新", "改革", "发明", "突破", "进步", "变化"]
    }
  },
  
  "number_unit_corrections": {
    "十万": ["是万", "时万", "实万", "石万", "拾万"],
    "百万": ["白万", "拜万", "败万", "摆万", "柏万"],
    "千万": ["钱万", "前万", "迁万", "浅万", "签万"],
    "一万": ["一晚", "一碗", "一弯", "一玩", "一湾"],
    "十亿": ["是亿", "时亿", "实亿", "石亿", "拾亿"],
    "百亿": ["白亿", "拜亿", "败亿", "摆亿", "柏亿"],
    "千亿": ["钱亿", "前亿", "迁亿", "浅亿", "签亿"],
    "万亿": ["晚亿", "碗亿", "弯亿", "玩亿", "湾亿"],
    
    "公里": ["公立", "公力", "工里", "功里", "公理"],
    "公斤": ["公金", "公今", "工斤", "功斤", "公近"],
    "公分": ["工分", "公份", "恭分", "功分", "公粉"],
    "平方米": ["平方迷", "平方密", "平房米", "评方米", "瓶方米"],
    "立方米": ["立方迷", "例方米", "立房米", "力方米", "厉方米"],
    "摄氏度": ["社事度", "设施度", "摄氏渡", "射氏度", "涉氏度"],
    "华氏度": ["华实度", "华式度", "花氏度", "华事度", "化氏度"],
    "毫米": ["豪米", "毫迷", "好米", "号米", "耗米"],
    "厘米": ["离米", "厘迷", "里米", "理米", "力米"],
    "千米": ["前米", "钱米", "迁米", "浅米", "签米"],
    
    "小时": ["小事", "小时", "消失", "小石", "小市"],
    "分钟": ["分种", "分中", "份钟", "分终", "分仲"],
    "秒钟": ["秒种", "秒中", "妙钟", "少钟", "抄钟"],
    "年": ["念", "拈", "粘", "年", "廿"],
    "月": ["乐", "月", "悦", "约", "跃"],
    "日": ["日", "热", "入", "肉", "容"],
    "天": ["田", "甜", "添", "天", "填"],
    "周": ["州", "舟", "洲", "粥", "轴"],
    "星期": ["星七", "星期", "兴期", "星气", "醒期"],
    
    "元": ["圆", "园", "源", "原", "远"],
    "角": ["脚", "叫", "觉", "较", "教"],
    "分": ["份", "芬", "纷", "粉", "奋"],
    "厘": ["离", "里", "理", "力", "立"],
    "毫": ["豪", "好", "号", "耗", "浩"],
    "块": ["快", "筷", "况", "狂", "框"],
    "毛": ["猫", "茅", "冒", "帽", "贸"],
    
    "度": ["渡", "肚", "杜", "独", "督"],
    "米": ["迷", "密", "蜜", "米", "秘"],
    "尺": ["尺", "吃", "赤", "池", "齿"],
    "寸": ["村", "存", "寸", "促", "醋"],
    "丈": ["张", "章", "掌", "长", "常"],
    "里": ["理", "力", "立", "利", "例"],
    "步": ["部", "布", "不", "补", "捕"]
  },
  
  "context_corrections": {
    "影视场景": {
      "关键词": ["电影", "电视剧", "演员", "导演", "拍摄", "剧组"],
      "专用词汇": {
        "杀青": ["沙青", "杀清", "撒青"],
        "开机": ["开鸡", "凯机", "开记"],
        "片场": ["篇场", "偏场", "便场"],
        "镜头": ["镜投", "境头", "静头"],
        "取景": ["去景", "娶景", "趣景"],
        "布景": ["部景", "不景", "补景"],
        "道具": ["到具", "倒具", "导具"],
        "服装": ["服状", "福装", "服庄"],
        "化妆": ["化状", "划妆", "话妆"],
        "造型": ["造行", "早型", "遭型"],
        "特技": ["特记", "特级", "特机"],
        "替身": ["替生", "体身", "梯身"],
        "武替": ["武体", "舞替", "武踢"],
        "文替": ["文体", "闻替", "温替"]
      }
    },
    "技术场景": {
      "关键词": ["技术", "科技", "电脑", "软件", "网络", "系统"],
      "专用词汇": {
        "算法": ["蒜法", "算花", "算发"],
        "程序": ["成序", "程需", "程续"],
        "代码": ["代吗", "待码", "代马"],
        "编程": ["编成", "便程", "编称"],
        "调试": ["调事", "条试", "掉试"],
        "测试": ["测事", "策试", "侧试"],
        "部署": ["部暑", "布署", "不署"],
        "运维": ["运为", "运位", "运围"],
        "优化": ["优话", "有化", "右化"],
        "升级": ["生级", "声级", "胜级"],
        "降级": ["降机", "将级", "江级"],
        "版本": ["班本", "版奔", "版笨"],
        "更新": ["更心", "各新", "跟新"],
        "修复": ["修服", "秀复", "修副"],
        "漏洞": ["楼洞", "漏动", "露洞"]
      }
    }
  },
  
  "homophone_errors": {
    "的地得": {
      "的": {
        "用法": "修饰名词",
        "例句": "美丽的花朵",
        "错误": ["地", "得"]
      },
      "地": {
        "用法": "修饰动词",
        "例句": "快速地跑步",
        "错误": ["的", "得"]
      },
      "得": {
        "用法": "补语标记",
        "例句": "跑得很快",
        "错误": ["的", "地"]
      }
    },
    "在再": {
      "在": {
        "用法": "表示存在或位置",
        "例句": "他在家里",
        "错误": ["再"]
      },
      "再": {
        "用法": "表示重复或继续",
        "例句": "再次尝试",
        "错误": ["在"]
      }
    },
    "做作": {
      "做": {
        "用法": "表示行为动作",
        "例句": "做作业",
        "错误": ["作"]
      },
      "作": {
        "用法": "表示创作或充当",
        "例句": "作文章",
        "错误": ["做"]
      }
    }
  },
  
  "sentence_patterns": {
    "疑问句标记": ["什么", "哪里", "怎么", "为什么", "怎样", "如何", "多少", "几时", "何时", "谁", "哪个", "哪些"],
    "感叹句标记": ["太", "真", "好", "很", "非常", "特别", "极其", "相当", "十分", "多么", "何等"],
    "转折词": ["但是", "不过", "然而", "可是", "只是", "只不过", "虽然", "尽管", "即使", "哪怕", "无论"],
    "递进词": ["而且", "并且", "同时", "另外", "还有", "此外", "况且", "更何况", "不但", "不仅"],
    "因果词": ["因为", "由于", "既然", "所以", "因此", "于是", "故此", "因而", "从而", "以致"],
    "时间词": ["然后", "接着", "随后", "接下来", "后来", "最后", "最终", "终于", "于是", "然后"]
  }
}
